satori/__init__.py
satori/schema.py
satori_client-0.1.8.dist-info/METADATA
satori_client-0.1.8.dist-info/WHEEL
satori_client-0.1.8.dist-info/RECORD
