Metadata-Version: 2.4
Name: satori-client
Version: 0.1.8
Summary: Python client for Satori database
Author-email: Sergio Valdes <svcu2310@gmail.com>
Requires-Python: >=3.7
Requires-Dist: uuid
Requires-Dist: websockets
